sysx/__init__.py
sysx/__main__.py
sysx-0.0.1.dist-info/METADATA
sysx-0.0.1.dist-info/WHEEL
sysx-0.0.1.dist-info/entry_points.txt
sysx-0.0.1.dist-info/top_level.txt
sysx-0.0.1.dist-info/RECORD
